LTRI_Funcs/__init__.py
LTRI_Funcs_knamdar-0.0.8.dist-info/LICENSE
LTRI_Funcs_knamdar-0.0.8.dist-info/METADATA
LTRI_Funcs_knamdar-0.0.8.dist-info/WHEEL
LTRI_Funcs_knamdar-0.0.8.dist-info/top_level.txt
LTRI_Funcs_knamdar-0.0.8.dist-info/RECORD
