Metadata-Version: 2.1
Name: LTRI-Funcs-knamdar
Version: 0.0.8
Summary: Handy functions used in LTRI Machine Learning Lab
Home-page: UNKNOWN
Author: Khashayar Namdar
Author-email: knamdar@uwo.ca
License: UNKNOWN
Platform: UNKNOWN
Classifier: Programming Language :: Python :: 3
Classifier: License :: OSI Approved :: MIT License
Classifier: Operating System :: OS Independent
